jp_aesthetic_terminal/__init__.py
jp_aesthetic_terminal/console.py
jp_aesthetic_terminal/wikipedia.py
jp_aesthetic_terminal-0.1.0.dist-info/entry_points.txt
jp_aesthetic_terminal-0.1.0.dist-info/LICENSE
jp_aesthetic_terminal-0.1.0.dist-info/WHEEL
jp_aesthetic_terminal-0.1.0.dist-info/METADATA
jp_aesthetic_terminal-0.1.0.dist-info/RECORD
